letterbomb/__init__.py
letterbomb/__main__.py
letterbomb/update_oui.py
letterbomb/included/oui_list.txt
letterbomb/included/bundled/APACHE-2.0.txt
letterbomb/included/bundled/CREDITS.txt
letterbomb/included/bundled/LICENSE.txt
letterbomb/included/bundled/README-BootMii.txt
letterbomb/included/bundled/README-HBC.txt
letterbomb/included/bundled/README.txt
letterbomb/included/bundled/boot.elf
letterbomb/included/bundled/bootmini.elf
letterbomb/included/templates/E.bin
letterbomb/included/templates/J.bin
letterbomb/included/templates/K.bin
letterbomb/included/templates/U.bin
letterbomb-4.1.dist-info/LICENSE.txt
letterbomb-4.1.dist-info/METADATA
letterbomb-4.1.dist-info/WHEEL
letterbomb-4.1.dist-info/top_level.txt
letterbomb-4.1.dist-info/RECORD
