Metadata-Version: 2.1
Name: letterbomb
Version: 4.1
Summary: A fork of the classic Wii hacking tool from fail0verflow
Author: WhoAteMyButter
License: MIT
Project-URL: Documentation, https://letterbomb.readthedocs.io
Project-URL: Source, https://gitlab.com/whoatemybutter/letterbomb
Project-URL: Changelog, https://gitlab.com/whoatemybutter/letterbomb/-/blob/master/CHANGELOG.md
Keywords: letterbomb,letter bomb,wii,failoverflow,fail0verflow,fail overflow,fail 0verflow,exploit,wii hack,hacking,jailbreak,jailbreaking
Classifier: Operating System :: OS Independent
Classifier: Development Status :: 5 - Production/Stable
Classifier: Programming Language :: Python :: 3 :: Only
Classifier: Programming Language :: Python :: 3.10
Classifier: Programming Language :: Python :: 3.11
Classifier: Programming Language :: Python :: 3.12
Classifier: License :: OSI Approved :: MIT License
Classifier: Topic :: Games/Entertainment
Requires-Python: >=3.10
License-File: LICENSE.txt
Provides-Extra: web
Requires-Dist: letterbomb-web ; extra == 'web'
